bespin/__init__.py
bespin/__main__.py
bespin/api.py
bespin/argparser.py
bespin/commands.py
bespin/config.py
bespin/dukeds.py
bespin/exceptions.py
bespin/jobtemplate.py
bespin/test_api.py
bespin/test_argparse.py
bespin/test_commands.py
bespin/test_config.py
bespin/test_dukeds.py
bespin/test_jobtemplate.py
bespin/test_tool_details.py
bespin/test_workflow.py
bespin/tool_details.py
bespin/workflow.py
bespin_cli-0.5.0.dist-info/LICENSE
bespin_cli-0.5.0.dist-info/METADATA
bespin_cli-0.5.0.dist-info/WHEEL
bespin_cli-0.5.0.dist-info/entry_points.txt
bespin_cli-0.5.0.dist-info/top_level.txt
bespin_cli-0.5.0.dist-info/RECORD
