Metadata-Version: 2.1
Name: bespin-cli
Version: 0.5.0
Summary: Command line tool to run workflows via Bespin.
Home-page: UNKNOWN
Author: John Bradley
Author-email: UNKNOWN
License: MIT
Platform: UNKNOWN
Classifier: Development Status :: 3 - Alpha
Classifier: Intended Audience :: Science/Research
Classifier: Topic :: Utilities
Classifier: License :: OSI Approved :: MIT License
Classifier: Programming Language :: Python :: 2.7
Classifier: Programming Language :: Python :: 3.4
Classifier: Programming Language :: Python :: 3.5
Classifier: Programming Language :: Python :: 3.6
Classifier: Programming Language :: Python :: 3.7
Requires-Dist: DukeDSClient
Requires-Dist: future
Requires-Dist: PyYAML
Requires-Dist: requests (>=2.20.0)
Requires-Dist: six
Requires-Dist: tabulate
Requires-Dist: cwltool (==1.0.20181217162649)
Requires-Dist: html5lib (==1.0.1)
